aws_signv4_apigateway/__init__.py
aws_signv4_apigateway/main.py
aws_signv4_apigateway-0.1.0.dist-info/DESCRIPTION.rst
aws_signv4_apigateway-0.1.0.dist-info/METADATA
aws_signv4_apigateway-0.1.0.dist-info/RECORD
aws_signv4_apigateway-0.1.0.dist-info/WHEEL
aws_signv4_apigateway-0.1.0.dist-info/entry_points.txt
aws_signv4_apigateway-0.1.0.dist-info/metadata.json
aws_signv4_apigateway-0.1.0.dist-info/top_level.txt
