Metadata-Version: 2.0
Name: aws-signv4-apigateway
Version: 0.1.0
Summary: Sign your request to invoke Amazon API Gateway REST API Endpoint with Signature Version 4
Home-page: https://github.com/rafikurnia/aws-signv4-apigateway
Author: Rafi Kurnia Putra
Author-email: rafi.putra@traveloka.com
License: Apache License 2.0
Platform: UNKNOWN
Requires-Python: >=3
Requires-Dist: requests-aws4auth (==0.9)
